README.txt
setup.py
silhouetteplot/__init__.py
silhouetteplot.egg-info/PKG-INFO
silhouetteplot.egg-info/SOURCES.txt
silhouetteplot.egg-info/dependency_links.txt
silhouetteplot.egg-info/top_level.txt